prefect_spark_on_k8s_operator/__init__.py
prefect_spark_on_k8s_operator/_version.py
prefect_spark_on_k8s_operator/app.py
prefect_spark_on_k8s_operator/constants.py
prefect_spark_on_k8s_operator/flows.py
prefect_spark_on_k8s_operator-0.1.2.dist-info/LICENSE
prefect_spark_on_k8s_operator-0.1.2.dist-info/METADATA
prefect_spark_on_k8s_operator-0.1.2.dist-info/WHEEL
prefect_spark_on_k8s_operator-0.1.2.dist-info/entry_points.txt
prefect_spark_on_k8s_operator-0.1.2.dist-info/top_level.txt
prefect_spark_on_k8s_operator-0.1.2.dist-info/RECORD
